rtl/go_to.v
`timescale 1ns / 1ps

module go_to(
	input clk,
	input rst,
	input [3:0] numb_sel,
	input signed [7:0] data,
	input [7:0] N,
	output reg [7:0] number
);

always @(posedge clk)
begin
	if(rst)
		number <= 8'd0;
	else 
	begin
		case(numb_sel)
			4'b1110 : number <= N;
			4'b1100 : 
			begin
				if(data > 0) number <= N;
				else number <= number+1;
			end
			4'b1101 :
			begin
				if(data < 0) number <= N;
				else number <= number+1;
			end
			default : number <= number+1;
		endcase
	end
end


endmodule

tb/tb_go_to.v
`timescale 1ns / 1ps

module tb_go_to;

reg clk = 1'b0,rst;
reg [3:0] numb_sel;
reg signed [7:0] data;
reg [7:0]N;

wire [7:0]number;

// for tb
//time t;

go_to DUT(clk,
	rst,
	numb_sel,
	data,
	N,
	number);

parameter cycle = 10,
	thold = 1,
	tsetup = 1;

always #(5) clk = ~clk;

task reset;
    begin
        rst = 1'b1; // Assert reset
        // Set other inputs to 'x' or known safe values during reset

        @(posedge clk); // Wait for a clock edge for synchronous reset to take effect
        #(thold);       // Wait for hold time

        if(number == 8'd0) begin
            $display("At time %0t: Reset operation successful. Program counter is %0d.", $time, number);
        end else begin
            $display("At time %0t: Reset operation FAILED. Program counter is %0d, expected 0.", $time, number);
        end

        rst = 1'b0; // De-assert reset
        // Wait for the next clock edge to ensure DUT sees rst=0 before next instruction
        @(posedge clk);
        #(cycle - thold - tsetup); // Wait for the rest of the cycle if needed
    end
endtask

task jump(input [7:0]n);
	begin
		rst = 1'b0;
		numb_sel = 4'b1110;
		N = n;

		@(posedge clk);
		#(thold);

		if(number == N)
		begin
			$display("At time t = %0t,The jump instr is working",$time);
			$display("At time t = %0t,The instr number generetad is %d, the given instr number is %d",$time, number, N);
		end
		else 
			$display("At time t = %0t,The jumb instr is not working",$time);

		{numb_sel, N} = 'bx;

		#(cycle-thold-tsetup);
	end
endtask

task jump_pos;
    input [7:0] n_target;
    input signed [7:0] d_val; // Ensure 'data' in DUT is also signed
    reg [7:0] prev_number; // Local variable to store PC before jump

    begin
        prev_number = number; // Capture current PC before new instruction

        rst = 1'b0;
        numb_sel = 4'b1100;
        N = n_target;
        data = d_val;

        @(posedge clk);
        #(thold);

        if (d_val > 0) begin // Expected to jump
            if (number == N) begin
                $display("At time %0t: JUMP_POS SUCCESS (data > 0). PC: %0d -> %0d, Target: %0d, Data: %0d.", $time, prev_number, number, N, d_val);
            end else begin
                $display("At time %0t: JUMP_POS FAILED (data > 0, no jump). PC: %0d , Expected: %0d, Data: %0d.", $time, prev_number, number, N, d_val);
            end
        end else begin // Expected to increment (no jump)
            if (number == prev_number + 1) begin
                $display("At time %0t: JUMP_POS SUCCESS (data <= 0, PC incremented). PC: %0d -> %0d, Data: %0d.", $time, prev_number, number, d_val);
            end else begin
                $display("At time %0t: JUMP_POS FAILED (data <= 0, incorrect PC). PC: %0d , Expected: %0d, Data: %0d.", $time, prev_number, number, d_val);
            end
        end

        {numb_sel, N, data} = 'bx; // De-assert control signals
        #(cycle-thold-tsetup);
    end
endtask

task jump_neg;
    input [7:0] n_target;
    input signed [7:0] d_val; // Ensure 'data' in DUT is also signed
    reg [7:0] prev_number; // Local variable to store PC before jump

    begin
        prev_number = number; // Capture current PC before new instruction

        rst = 1'b0;
        numb_sel = 4'b1101;
        N = n_target;
        data = d_val;

        @(posedge clk);
        #(thold);

        if (d_val < 0) begin // Expected to jump
            if (number == N) begin
                $display("At time %0t: jumb_neg SUCCESS (data > 0). PC: %0d -> %0d, Target: %0d, Data: %0d.", $time, prev_number, number, N, d_val);
            end else begin
                $display("At time %0t: jumb_neg FAILED (data > 0, no jump). PC: %0d , Expected: %0d, Data: %0d.", $time, prev_number, number, N, d_val);
            end
        end else begin // Expected to increment (no jump)
            if (number == prev_number + 1) begin
                $display("At time %0t: jumb_neg SUCCESS (data <= 0, PC incremented). PC: %0d -> %0d, Data: %0d.", $time, prev_number, number, d_val);
            end else begin
                $display("At time %0t: jumb_neg FAILED (data <= 0, incorrect PC). PC: %0d , Expected: %0d, Data: %0d.", $time, prev_number, number, d_val);
            end
        end

        {numb_sel, N, data} = 'bx; // De-assert control signals
        #(cycle-thold-tsetup);
    end
endtask
// reset();
// jump(N);
// jump_pos(N, d);
// jump_neg(N, d);
//
// N is instr no to jump
// d is data

initial begin

    $dumpfile("go_to.vcd");
	$dumpvars(0, tb_go_to);
	reset();
	repeat(4)
	begin
		@(posedge clk);
		$display("At time t= %0t, the pc %d is at without any instructions", $time, number);
	end
	jump(5);
	jump_pos(4, 5);
	jump_pos(8, -4);
	jump_neg(10, -3);
	jump_neg(15, 4);
	reset();
	$monitor("At time t= %0t, the number is %d", $time, number);
	$finish;

end


endmodule

sim/go_to.vcd
$date
	Wed Sep 16 16:28:04 2026
$end
$version
	Icarus Verilog
$end
$timescale
	1ps
$end
$scope module tb_go_to $end
$var wire 8 ! number [7:0] $end
$var reg 8 " N [7:0] $end
$var reg 1 # clk $end
$var reg 8 $ data [7:0] $end
$var reg 4 % numb_sel [3:0] $end
$var reg 1 & rst $end
$scope module DUT $end
$var wire 8 ' N [7:0] $end
$var wire 1 # clk $end
$var wire 8 ( data [7:0] $end
$var wire 4 ) numb_sel [3:0] $end
$var wire 1 & rst $end
$var reg 8 * number [7:0] $end
$upscope $end
$scope task jump $end
$var reg 8 + n [7:0] $end
$upscope $end
$scope task jump_neg $end
$var reg 8 , d_val [7:0] $end
$var reg 8 - n_target [7:0] $end
$var reg 8 . prev_number [7:0] $end
$upscope $end
$scope task jump_pos $end
$var reg 8 / d_val [7:0] $end
$var reg 8 0 n_target [7:0] $end
$var reg 8 1 prev_number [7:0] $end
$upscope $end
$scope task reset $end
$upscope $end
$upscope $end
$enddefinitions $end
#0
$dumpvars
bx 1
bx 0
bx /
bx .
bx -
bx ,
bx +
bx *
bx )
bx (
bx '
1&
bx %
bx $
0#
bx "
bx !
$end
#5000
b0 !
b0 *
1#
#6000
0&
#10000
0#
#15000
b1 !
b1 *
1#
#20000
0#
#25000
b10 !
b10 *
1#
#30000
0#
#35000
b11 !
b11 *
1#
#40000
0#
#45000
b100 !
b100 *
1#
#50000
0#
#55000
b101 !
b101 *
b101 "
b101 '
b1110 %
b1110 )
b101 +
1#
#60000
0#
#65000
1#
#66000
bx %
bx )
bx "
bx '
#70000
0#
#74000
b101 $
b101 (
b100 "
b100 '
b1100 %
b1100 )
b101 1
b101 /
b100 0
#75000
b100 !
b100 *
1#
#76000
bx %
bx )
bx "
bx '
bx $
bx (
#80000
0#
#84000
b11111100 $
b11111100 (
b1000 "
b1000 '
b1100 %
b1100 )
b100 1
b11111100 /
b1000 0
#85000
b101 !
b101 *
1#
#86000
bx %
bx )
bx "
bx '
bx $
bx (
#90000
0#
#94000
b11111101 $
b11111101 (
b1010 "
b1010 '
b1101 %
b1101 )
b101 .
b11111101 ,
b1010 -
#95000
b1010 !
b1010 *
1#
#96000
bx %
bx )
bx "
bx '
bx $
bx (
#100000
0#
#104000
b100 $
b100 (
b1111 "
b1111 '
b1101 %
b1101 )
b1010 .
b100 ,
b1111 -
#105000
b1011 !
b1011 *
1#
#106000
bx %
bx )
bx "
bx '
bx $
bx (
#110000
0#
#114000
1&
#115000
b0 !
b0 *
1#
#116000
0&
#120000
0#
#125000
b1 !
b1 *
1#
